example2410/__init__.py
example2410/ex_model.py
example2410/helper.py
example2410-1.0.14.dist-info/LICENSE
example2410-1.0.14.dist-info/METADATA
example2410-1.0.14.dist-info/WHEEL
example2410-1.0.14.dist-info/RECORD
