Metadata-Version: 2.3
Name: example2410
Version: 1.0.14
Summary: Moneybird SDK for example2024
License: MIT
Keywords: nlp,topicmodel,poisson factorization,variational inference,textanalysis
Author: Bernd Prostmaier
Author-email: b.prostmaier@icloud.com
Requires-Python: >=3.10,<3.12
Classifier: License :: OSI Approved :: MIT License
Classifier: Programming Language :: Python :: 3
Classifier: Programming Language :: Python :: 3.10
Classifier: Programming Language :: Python :: 3.11
Requires-Dist: cmake (==3.31.6)
Requires-Dist: matplotlib
Requires-Dist: numpy (>=1.23,<2.0)
Requires-Dist: pandas
Requires-Dist: scikit_learn (==1.6.1)
Requires-Dist: scipy (==1.15.2)
Requires-Dist: seaborn (==0.13.2)
Requires-Dist: tensorflow (==2.18)
Requires-Dist: tensorflow_probability (==0.25)
Requires-Dist: tf-keras (==2.18)
Project-URL: Homepage, https://github.com/BPro2410/example_workflow
Project-URL: Repository, https://github.com/BPro2410/example_workflow
